curlenetes.py
curlenetes-0.1.1.dist-info/licenses/LICENSE
curlenetes-0.1.1.dist-info/METADATA
curlenetes-0.1.1.dist-info/WHEEL
curlenetes-0.1.1.dist-info/entry_points.txt
curlenetes-0.1.1.dist-info/top_level.txt
curlenetes-0.1.1.dist-info/RECORD
