Metadata-Version: 2.4
Name: curlenetes
Version: 0.1.1
Summary: A small kubectl and curl wrapper to make http requests to k8s's services
Requires-Python: >=3.6
License-File: LICENSE
Dynamic: license-file
